temu_captcha_solver/__init__.py
temu_captcha_solver/api.py
temu_captcha_solver/async_plawright_util.py
temu_captcha_solver/asyncplaywrightsolver.py
temu_captcha_solver/asyncsolver.py
temu_captcha_solver/captchatype.py
temu_captcha_solver/download_crx.py
temu_captcha_solver/downloader.py
temu_captcha_solver/geometry.py
temu_captcha_solver/launcher.py
temu_captcha_solver/models.py
temu_captcha_solver/parsers.py
temu_captcha_solver/plawright_util.py
temu_captcha_solver/playwrightsolver.py
temu_captcha_solver/selectors.py
temu_captcha_solver/selenium_util.py
temu_captcha_solver/seleniumsolver.py
temu_captcha_solver/syncsolver.py
temu_captcha_solver/solver_commons/__init__.py
temu_captcha_solver/solver_commons/exceptions.py
temu_captcha_solver/solver_commons/two_image.py
temu_captcha_solver/tests/__init__.py
temu_captcha_solver/tests/test_api.py
temu_captcha_solver/tests/test_asyncplaywrightsolver.py
temu_captcha_solver/tests/test_download_crx.py
temu_captcha_solver/tests/test_downloader.py
temu_captcha_solver/tests/test_launcher.py
temu_captcha_solver/tests/test_playwrightsolver.py
temu_captcha_solver/tests/test_seleniumsolver.py
temu_captcha_solver/tests/test_solver_commons.py
temu_captcha_solver-0.6.8.dist-info/METADATA
temu_captcha_solver-0.6.8.dist-info/WHEEL
temu_captcha_solver-0.6.8.dist-info/top_level.txt
temu_captcha_solver-0.6.8.dist-info/RECORD
