Metadata-Version: 2.4
Name: temu-captcha-solver
Version: 0.6.8
Summary: This package integrates with Selenium or Playwright to solve any Temu captcha in one line of code.
Author-email: Toughdata LLC <greg@toughdata.net>
Project-URL: Homepage, https://www.sadcaptcha.com
Project-URL: Source, https://github.com/gbiz123/temu-captcha-solver/
Keywords: temu,captcha,solver,selenium,playwright
Classifier: Intended Audience :: Developers
Classifier: Topic :: Software Development :: Build Tools
Classifier: Programming Language :: Python :: 3.10
Classifier: Programming Language :: Python :: 3.11
Classifier: Programming Language :: Python :: 3.12
Classifier: Programming Language :: Python :: 3 :: Only
Requires-Python: >=3.10
Requires-Dist: selenium
Requires-Dist: webdriver-manager
Requires-Dist: pydantic
Requires-Dist: requests
Requires-Dist: pytest
Requires-Dist: pytest-asyncio
Requires-Dist: playwright
Requires-Dist: playwright-stealth
Requires-Dist: undetected_chromedriver
Requires-Dist: setuptools
Requires-Dist: nodriver
